DtCrawlEngine-1.2.6.dist-info/DESCRIPTION.rst
DtCrawlEngine-1.2.6.dist-info/METADATA
DtCrawlEngine-1.2.6.dist-info/RECORD
DtCrawlEngine-1.2.6.dist-info/WHEEL
DtCrawlEngine-1.2.6.dist-info/entry_points.txt
DtCrawlEngine-1.2.6.dist-info/metadata.json
DtCrawlEngine-1.2.6.dist-info/top_level.txt
engine/__init__.py
engine/_deprecate.py
engine/app.py
engine/config.py
engine/default_engine.conf
engine/eggstorage.py
engine/eggutils.py
engine/environ.py
engine/interfaces.py
engine/launcher.py
engine/metrics.py
engine/poller.py
engine/runner.py
engine/scheduler.py
engine/script.py
engine/spiderqueue.py
engine/sqlite.py
engine/txapp.py
engine/utils.py
engine/version.ini
engine/webservice.py
engine/website.py
engine/console/__init__.py
engine/console/engine_run.py
