Metadata-Version: 2.0
Name: DtCrawlEngine
Version: 1.2.6
Summary: 一个使用http api提供爬虫脚本服务的引擎
Home-page: http://git.dtstack.cn/dtstack/DtCrawlEngine.git
Author: Scrapy developers
Author-email: run.cao.xu@gmail.com
License: BSD
Platform: UNKNOWN
Classifier: Programming Language :: Python
Classifier: Programming Language :: Python :: 2.7
Classifier: Programming Language :: Python :: 3
Classifier: Programming Language :: Python :: 3.4
Classifier: Programming Language :: Python :: 3.5
Classifier: Programming Language :: Python :: 3.6
Classifier: License :: OSI Approved :: BSD License
Classifier: Operating System :: OS Independent
Classifier: Development Status :: 5 - Production/Stable
Classifier: Environment :: Console
Classifier: Environment :: No Input/Output (Daemon)
Classifier: Topic :: Internet :: WWW/HTTP
Requires-Dist: Scrapy (>=1.0)
Requires-Dist: Twisted (>=8.0)
Requires-Dist: enum-compat
Requires-Dist: six
